player/__init__.py
player/app.py
player/const.py
player/data_manager.py
player/printer.py
player/program_launcher.py
p_player-0.1.0.dist-info/METADATA
p_player-0.1.0.dist-info/WHEEL
p_player-0.1.0.dist-info/entry_points.txt
p_player-0.1.0.dist-info/top_level.txt
p_player-0.1.0.dist-info/RECORD
