Metadata-Version: 2.1
Name: p-player
Version: 0.1.0
Summary: UNKNOWN
Home-page: UNKNOWN
Author: UNKNOWN
Author-email: UNKNOWN
License: UNKNOWN
Platform: UNKNOWN
Requires-Dist: PyYAML (==6.0.1)
Requires-Dist: inquirer (==3.1.3)
